django_jssor-0.3.2.dist-info/metadata.json
django_jssor-0.3.2.dist-info/WHEEL
django_jssor-0.3.2.dist-info/METADATA
django_jssor-0.3.2.dist-info/DESCRIPTION.rst
django_jssor-0.3.2.dist-info/RECORD
django_jssor-0.3.2.dist-info/top_level.txt
jssor/__init__.py
jssor/admin.py
jssor/views.py
jssor/tests.py
jssor/apps.py
jssor/models.py
jssor/templates/jssor/banner_slider.html
jssor/templates/jssor/full_width_slider.html
jssor/templates/jssor/bootstrap_slider.html
jssor/locale/fr/LC_MESSAGES/django.po
jssor/locale/fr/LC_MESSAGES/django.mo
jssor/migrations/__init__.py
jssor/migrations/__init__.pyc
jssor/migrations/0001_initial.pyc
jssor/static/jssor/img/t01.png
jssor/static/jssor/img/b12.png
jssor/static/jssor/img/loading2.gif
jssor/static/jssor/img/b16.png
jssor/static/jssor/img/a09.png
jssor/static/jssor/img/b03.png
jssor/static/jssor/img/a19.png
jssor/static/jssor/img/b10.png
jssor/static/jssor/img/b21.png
jssor/static/jssor/img/a01.png
jssor/static/jssor/img/Icon-Slider-12-No-jQuery.png
jssor/static/jssor/img/b07.png
jssor/static/jssor/img/close.png
jssor/static/jssor/img/Icon-Slider-12-jQuery.png
jssor/static/jssor/img/b05.png
jssor/static/jssor/img/back.jpg
jssor/static/jssor/img/b02.png
jssor/static/jssor/img/a03.png
jssor/static/jssor/img/a13.png
jssor/static/jssor/img/browser-icons.png
jssor/static/jssor/img/a12.png
jssor/static/jssor/img/a08.png
jssor/static/jssor/img/a10.png
jssor/static/jssor/img/a22.png
jssor/static/jssor/img/b18.png
jssor/static/jssor/img/b06.png
jssor/static/jssor/img/a15.png
jssor/static/jssor/img/b20.png
jssor/static/jssor/img/a18.png
jssor/static/jssor/img/a14.png
jssor/static/jssor/img/a21.png
jssor/static/jssor/img/a02.png
jssor/static/jssor/img/a20.png
jssor/static/jssor/img/play.png
jssor/static/jssor/img/b11.png
jssor/static/jssor/img/b17.png
jssor/static/jssor/img/a07.png
jssor/static/jssor/img/b14.png
jssor/static/jssor/img/a04.png
jssor/static/jssor/img/a06.png
jssor/static/jssor/img/a16.png
jssor/static/jssor/img/b13.png
jssor/static/jssor/img/a17.png
jssor/static/jssor/img/a11.png
jssor/static/jssor/img/loading.gif
jssor/static/jssor/js/jssor.player.ytiframe.js
jssor/static/jssor/js/jssor.slider.min.js
