Metadata-Version: 2.0
Name: django-jssor
Version: 0.3.2
Summary: Jssor slideshows for Django
Home-page: https://github.com/synw/django-jssor
Author: synw
Author-email: synwe@yahoo.com
License: UNKNOWN
Download-URL: https://github.com/synw/django-jssor/releases/tag/0.3.2
Keywords: django,slideshows,jssor
Platform: UNKNOWN
Classifier: Development Status :: 3 - Alpha
Classifier: Framework :: Django :: 1.8
Classifier: Intended Audience :: Developers
Classifier: License :: OSI Approved :: MIT License
Classifier: Programming Language :: Python :: 2.7
Requires-Dist: Django (>=1.8.0)
Requires-Dist: django-autoslug
Requires-Dist: Pillow
